Metadata-Version: 2.1
Name: vcs-uploader
Version: 1.0.4
Summary: uploader for vcs, work with libupdate
Home-page: https://github.com/gen-iot/vcs-uploader
Author: suzhen
Author-email: suzhen@homeinpocket.net
License: MIT License
Platform: all
Classifier: Programming Language :: Python :: 3.0
Classifier: Topic :: Software Development :: Code Generators
Classifier: Operating System :: OS Independent
Requires-Python: >=3.4
